djeneralize-1.3.dist-info/DESCRIPTION.rst
djeneralize-1.3.dist-info/RECORD
djeneralize-1.3.dist-info/metadata.json
djeneralize-1.3.dist-info/top_level.txt
djeneralize-1.3.dist-info/METADATA
djeneralize-1.3.dist-info/WHEEL
djeneralize/query.py
djeneralize/manager.py
djeneralize/utils.py
djeneralize/fields.py
djeneralize/models.py
djeneralize/__init__.py
tests/test_base.py
tests/test_managers.py
tests/test_integration.py
tests/test_fields.py
tests/fixtures.py
tests/__init__.py
tests/test_djeneralize/manage.py
tests/test_djeneralize/urls.py
tests/test_djeneralize/settings.py
tests/test_djeneralize/__init__.py
tests/test_djeneralize/fruit/models.py
tests/test_djeneralize/fruit/__init__.py
tests/test_djeneralize/producers/models.py
tests/test_djeneralize/producers/__init__.py
tests/test_djeneralize/writing/models.py
tests/test_djeneralize/writing/__init__.py
